gutenberg_cleaner.py
_cleaning_options/__init__.py
_cleaning_options/cleaner.py
_cleaning_options/cleaning_options.py
_cleaning_options/strip_headers.py
gutenberg_cleaner-0.1.6.dist-info/LICENSE.md
gutenberg_cleaner-0.1.6.dist-info/METADATA
gutenberg_cleaner-0.1.6.dist-info/WHEEL
gutenberg_cleaner-0.1.6.dist-info/top_level.txt
gutenberg_cleaner-0.1.6.dist-info/RECORD
