Metadata-Version: 2.1
Name: gutenberg-cleaner
Version: 0.1.6
Summary: cleans gutenberg dataset books
Home-page: https://github.com/kiasar/gutenberg_cleaner
Author: UNKNOWN
Author-email: mohsenikiasari@ce.sharif.edu
License: MIT
Platform: UNKNOWN
Classifier: Programming Language :: Python
Classifier: Programming Language :: Python :: 3.6
Classifier: Programming Language :: Python :: 3.7
Classifier: Operating System :: OS Independent
Requires-Dist: nltk
